invenio_theme_iform/__about__.py
invenio_theme_iform/__init__.py
invenio_theme_iform/config.py
invenio_theme_iform/ext.py
invenio_theme_iform/search.py
invenio_theme_iform/views.py
invenio_theme_iform/webpack.py
invenio_theme_iform/assets/semantic-ui/js/invenio_theme_iform/theme.js
invenio_theme_iform/assets/semantic-ui/js/invenio_theme_iform/unlock.js
invenio_theme_iform/assets/semantic-ui/less/invenio_theme_iform/accounts.less
invenio_theme_iform/assets/semantic-ui/less/invenio_theme_iform/communities.less
invenio_theme_iform/assets/semantic-ui/less/invenio_theme_iform/deposit.less
invenio_theme_iform/assets/semantic-ui/less/invenio_theme_iform/footer.less
invenio_theme_iform/assets/semantic-ui/less/invenio_theme_iform/frontpage.less
invenio_theme_iform/assets/semantic-ui/less/invenio_theme_iform/header.less
invenio_theme_iform/assets/semantic-ui/less/invenio_theme_iform/login.less
invenio_theme_iform/assets/semantic-ui/less/invenio_theme_iform/macros.less
invenio_theme_iform/assets/semantic-ui/less/invenio_theme_iform/overrides.less
invenio_theme_iform/assets/semantic-ui/less/invenio_theme_iform/record.less
invenio_theme_iform/assets/semantic-ui/less/invenio_theme_iform/search.less
invenio_theme_iform/assets/semantic-ui/less/invenio_theme_iform/theme.less
invenio_theme_iform/assets/semantic-ui/less/invenio_theme_iform/variables.less
invenio_theme_iform/assets/semantic-ui/less/invenio_theme_iform/fonts/SourceSansPro/OFL.txt
invenio_theme_iform/assets/semantic-ui/less/invenio_theme_iform/fonts/SourceSansPro/SourceSansPro-Italic.ttf
invenio_theme_iform/assets/semantic-ui/less/invenio_theme_iform/fonts/SourceSansPro/SourceSansPro-Regular.ttf
invenio_theme_iform/static/favicon.ico
invenio_theme_iform/static/extra/orcid.png
invenio_theme_iform/static/images/SFI_logo.png
invenio_theme_iform/static/images/cyan_400x400.png
invenio_theme_iform/static/images/dark_blue_400x400.png
invenio_theme_iform/static/images/diamond.svg
invenio_theme_iform-2025.6.6.4.dist-info/METADATA
invenio_theme_iform-2025.6.6.4.dist-info/WHEEL
invenio_theme_iform-2025.6.6.4.dist-info/entry_points.txt
invenio_theme_iform-2025.6.6.4.dist-info/licenses/AUTHORS.rst
invenio_theme_iform-2025.6.6.4.dist-info/licenses/LICENSE
invenio_theme_iform-2025.6.6.4.dist-info/RECORD
