Metadata-Version: 2.4
Name: invenio-theme-iform
Version: 2025.6.6.4
Summary: Invenio module for the I-Form theme.
Project-URL: Homepage, https://github.com/Cian-H/invenio-theme-iform
Project-URL: Issues, https://github.com/Cian-H/invenio-theme-iform/issues
Author-email: I-Form Advanced Research Manufacturing Research Centre <cian.hughes@dcu.ie>
License-Expression: MIT
License-File: AUTHORS.rst
License-File: LICENSE
Keywords: I-Form,invenio,invenioRDM,theme
Classifier: Development Status :: 3 - Alpha
Classifier: Environment :: Web Environment
Classifier: Intended Audience :: Developers
Classifier: Operating System :: OS Independent
Classifier: Programming Language :: Python
Classifier: Programming Language :: Python :: 3.10
Classifier: Programming Language :: Python :: 3.11
Classifier: Programming Language :: Python :: 3.12
Classifier: Programming Language :: Python :: 3.13
Classifier: Topic :: Internet :: WWW/HTTP :: Dynamic Content
Classifier: Topic :: Software Development :: Libraries :: Python Modules
Requires-Python: <3.14,>=3.10
Requires-Dist: invenio-assets>=2.0.0
Requires-Dist: invenio-config-iform>=2025.5.20.1
Requires-Dist: invenio-records-global-search>=0.0.1
Requires-Dist: invenio-records-lom>=0.16.0
Requires-Dist: invenio-records-marc21>=0.21.0
